blowcurve/__init__.py
blowcurve/crypt.py
blowcurve/keys.py
blowcurve/test.py
blowcurve-1.0.0.dist-info/LICENSE.txt
blowcurve-1.0.0.dist-info/METADATA
blowcurve-1.0.0.dist-info/WHEEL
blowcurve-1.0.0.dist-info/top_level.txt
blowcurve-1.0.0.dist-info/RECORD
