Metadata-Version: 2.1
Name: blowcurve
Version: 1.0.0
Summary: Simple library for Blowfish / ECC encryption and digital signatures.
Home-page: https://github.com/origamizyt/blowcurve
Author: origamizyt
Author-email: zhaoyitong18@163.com
License: MIT
Platform: UNKNOWN
Classifier: Programming Language :: Python :: 3
Classifier: License :: OSI Approved :: MIT License
Classifier: Operating System :: OS Independent
Requires-Python: >=3
Requires-Dist: PyCryptodome
Requires-Dist: ecdsa
